magD/__init__.py
magD/city.py
magD/event.py
magD/iris.py
magD/location.py
magD/magD.py
magD/origin.py
magD/pickle.py
magD/plotMagD.py
magD/scnl.py
magD/seis.py
magD/solution.py
obs/__init__.py
obs/min_mode.py
obs/obs.py
obs/obs_mode_v_freq.py
test/__init__.py
test/test_azimuthal_gap.py
test/test_iris.py
test/test_magd.py
test/test_origin.py
test/test_scnl.py
test/test_seis.py
test/test_solution.py
test/fixtures/__init__.py
test/fixtures/seis_data.py
MagD-2.3.dist-info/METADATA
MagD-2.3.dist-info/WHEEL
MagD-2.3.dist-info/top_level.txt
MagD-2.3.dist-info/RECORD
