Metadata-Version: 2.1
Name: MagD
Version: 2.3
Summary: A map based packaged to analyze seimic network perfromance
Home-page: https://github.com/pnsn/magD
Author: Jon Connolly
Author-email: joncon@uw.edu
License: UNKNOWN
Platform: UNKNOWN
Classifier: Programming Language :: Python :: 3
Classifier: License :: OSI Approved :: MIT License
Classifier: Operating System :: OS Independent
